{"chunk_definitions":[{"chunk_id":"cib90dllx0n3n","chunk_label":"unnamed-chunk-1","document_id":"883111A4","expansion_state":0,"options":{"engine":"r","label":"unnamed-chunk-1"},"row":16,"row_count":1,"visible":true},{"chunk_id":"cuhl5l5lnfiix","chunk_label":"unnamed-chunk-2","document_id":"883111A4","expansion_state":0,"options":{"engine":"r","label":"unnamed-chunk-3"},"row":31,"row_count":1,"visible":true},{"chunk_id":"czjdsmw6x28vc","chunk_label":"unnamed-chunk-3","document_id":"883111A4","expansion_state":0,"options":{"engine":"r","label":"unnamed-chunk-24"},"row":41,"row_count":1,"visible":true},{"chunk_id":"cs8y4x9tcif10","chunk_label":"unnamed-chunk-4","document_id":"883111A4","expansion_state":0,"options":{"engine":"r","label":"unnamed-chunk-22"},"row":53,"row_count":1,"visible":true},{"chunk_id":"cqquz88lns81s","chunk_label":"unnamed-chunk-5","document_id":"883111A4","expansion_state":0,"options":{"engine":"r","label":"unnamed-chunk-21"},"row":58,"row_count":1,"visible":true},{"chunk_id":"corspabntg26u","chunk_label":"unnamed-chunk-6","document_id":"883111A4","expansion_state":0,"options":{"engine":"r","label":"unnamed-chunk-20"},"row":64,"row_count":1,"visible":true},{"chunk_id":"cnlud4m6yqg1s","chunk_label":"unnamed-chunk-7","document_id":"883111A4","expansion_state":0,"options":{"engine":"r","label":"unnamed-chunk-19"},"row":70,"row_count":1,"visible":true},{"chunk_id":"cuirbu6ypdk1b","chunk_label":"unnamed-chunk-8","document_id":"883111A4","expansion_state":0,"options":{"engine":"r","label":"unnamed-chunk-18"},"row":77,"row_count":1,"visible":true},{"chunk_id":"cm26dv2oye1zn","chunk_label":"unnamed-chunk-9","document_id":"883111A4","expansion_state":0,"options":{"engine":"r","label":"unnamed-chunk-28"},"row":81,"row_count":1,"visible":true},{"chunk_id":"cgg099ha5litj","chunk_label":"unnamed-chunk-10","document_id":"883111A4","expansion_state":0,"options":{"engine":"r","label":"unnamed-chunk-29"},"row":85,"row_count":1,"visible":true},{"chunk_id":"c9xgvlg4gbia5","chunk_label":"unnamed-chunk-11","document_id":"883111A4","expansion_state":0,"options":{"engine":"r","label":"unnamed-chunk-30"},"row":89,"row_count":1,"visible":true},{"chunk_id":"c2ea50c2jrn8g","chunk_label":"unnamed-chunk-12","document_id":"883111A4","expansion_state":0,"options":{"engine":"r","label":"unnamed-chunk-1"},"row":93,"row_count":1,"visible":true},{"chunk_id":"cjwj1kekq3gx0","chunk_label":"unnamed-chunk-13","document_id":"883111A4","expansion_state":0,"options":{"engine":"r","label":"unnamed-chunk-7"},"row":103,"row_count":1,"visible":true},{"chunk_id":"ct93c16qrsc25","chunk_label":"unnamed-chunk-14","document_id":"883111A4","expansion_state":0,"options":{"engine":"r","label":"unnamed-chunk-10"},"row":112,"row_count":1,"visible":true},{"chunk_id":"cq4lqwjildxa9","chunk_label":"unnamed-chunk-15","document_id":"883111A4","expansion_state":0,"options":{"engine":"r","label":"unnamed-chunk-20"},"row":142,"row_count":1,"visible":true},{"chunk_id":"cx8kumrwe7rhx","chunk_label":"unnamed-chunk-16","document_id":"883111A4","expansion_state":0,"options":{"engine":"r","label":"unnamed-chunk-64"},"row":150,"row_count":1,"visible":true}],"doc_write_time":1516671284}